tinystructlog/__init__.py
tinystructlog/core.py
tinystructlog/py.typed
tinystructlog-0.1.2.dist-info/METADATA
tinystructlog-0.1.2.dist-info/WHEEL
tinystructlog-0.1.2.dist-info/licenses/LICENSE
tinystructlog-0.1.2.dist-info/RECORD
