Metadata-Version: 2.4
Name: tinystructlog
Version: 0.1.2
Summary: Minimalistic context-aware structured logging for Python
Project-URL: Homepage, https://github.com/Aprova-GmbH/tinystructlog
Project-URL: Documentation, https://tinystructlog.readthedocs.io
Project-URL: Repository, https://github.com/Aprova-GmbH/tinystructlog
Project-URL: Issues, https://github.com/Aprova-GmbH/tinystructlog/issues
Project-URL: Changelog, https://github.com/Aprova-GmbH/tinystructlog/blob/main/CHANGELOG.md
Author-email: Andrey Vykhodtsev <vya@aprova.ch>
License: MIT
License-File: LICENSE
Keywords: async,context,contextvars,logging,structured-logging,thread-safe
Classifier: Development Status :: 4 - Beta
Classifier: Intended Audience :: Developers
Classifier: License :: OSI Approved :: MIT License
Classifier: Operating System :: OS Independent
Classifier: Programming Language :: Python :: 3
Classifier: Programming Language :: Python :: 3.11
Classifier: Programming Language :: Python :: 3.12
Classifier: Programming Language :: Python :: 3.13
Classifier: Topic :: Software Development :: Libraries :: Python Modules
Classifier: Topic :: System :: Logging
Classifier: Typing :: Typed
Requires-Python: >=3.11
Provides-Extra: dev
Requires-Dist: black>=24.0.0; extra == 'dev'
Requires-Dist: build>=1.0.0; extra == 'dev'
Requires-Dist: pytest-asyncio>=0.23.5; extra == 'dev'
Requires-Dist: pytest-cov>=4.1.0; extra == 'dev'
Requires-Dist: pytest>=8.0.0; extra == 'dev'
Requires-Dist: ruff>=0.3.0; extra == 'dev'
Requires-Dist: sphinx-rtd-theme>=2.0.0; extra == 'dev'
Requires-Dist: sphinx>=7.2.0; extra == 'dev'
Requires-Dist: twine>=5.0.0; extra == 'dev'
